[
  {
    "id": "13910",
    "name": "Використання факторів механічної природи з лікувальною метою",
    "parent_id": "12799",
    "is_final": "1"
  },
  {
    "id": "13912",
    "name": "Гідротерапія",
    "parent_id": "12799",
    "is_final": "1"
  },
  {
    "id": "13909",
    "name": "Лазеротерапія, лазеропунктура: принципи дії, застосування",
    "parent_id": "12799",
    "is_final": "1"
  },
  {
    "id": "13911",
    "name": "Лікування штучно-зміненим середовищем, аероіонотерапія, аерозоль і електроаерозельтерапія, галотерапія, киснева терапія",
    "parent_id": "12799",
    "is_final": "1"
  },
  {
    "id": "13034",
    "name": "Магнітотерапія: принципи дії, механізм роботи",
    "parent_id": "12799",
    "is_final": "1"
  },
  {
    "id": "17443",
    "name": "ПМК №1 з преформованих фізичних чинників.",
    "parent_id": "12799",
    "is_final": "1"
  },
  {
    "id": "12801",
    "name": "Роль і місце імпульсної електротерапії серед реабілітаційних технологій",
    "parent_id": "12799",
    "is_final": "1"
  },
  {
    "id": "12800",
    "name": "Т1 Основні методи електротерапії і біофізіологічне обґрунтування їх застосування. Електротерапія постійним струмом в реабілітації хворих",
    "parent_id": "12799",
    "is_final": "1"
  },
  {
    "id": "13908",
    "name": "УФО-терапія",
    "parent_id": "12799",
    "is_final": "1"
  }
]