[
  {
    "id": "25745",
    "name": "M2 Спеціальні питання гігієни та екології",
    "parent_id": "1458",
    "is_final": "1"
  },
  {
    "id": "12659",
    "name": "Т1 Комплексна оцінка фізичного розвитку дітей та підлітків, визначення груп здоров'я та фізичного виховання",
    "parent_id": "1458",
    "is_final": "1"
  },
  {
    "id": "29548",
    "name": "Т10 Методика організації і проведення гігієнічної експертизи води і продовольства в польових умовах з допомогою табельних засобів",
    "parent_id": "1458",
    "is_final": "1"
  },
  {
    "id": "16347",
    "name": "Т18 Здоровий спосіб життя та особиста гігієна",
    "parent_id": "1458",
    "is_final": "1"
  },
  {
    "id": "12660",
    "name": "Т2 Методика визначення готовності дітей до систематичного навчання у школі",
    "parent_id": "1458",
    "is_final": "1"
  },
  {
    "id": "29541",
    "name": "Т3 Методика гігієнічної оцінки розташування та планування ділянки лікувально-профілактичного закладу",
    "parent_id": "1458",
    "is_final": "1"
  },
  {
    "id": "29542",
    "name": "Т4 Методика гігієнічної оцінки внутрішнього планування та санітарно-технічного благоустрою лікарні",
    "parent_id": "1458",
    "is_final": "1"
  },
  {
    "id": "29543",
    "name": "Т5 Методика гігієнічної оцінки умов перебування хворих та праці медичного персоналу в лікувальних закладах",
    "parent_id": "1458",
    "is_final": "1"
  },
  {
    "id": "29544",
    "name": "Т6 Методика оцінки радіаційної обстановки та параметрів захисту від зовнішнього та внутрішнього опромінення",
    "parent_id": "1458",
    "is_final": "1"
  },
  {
    "id": "29545",
    "name": "Т7 Методика організації та проведення санепідрозвідки джерел водопостачання та оцінки якості води в польових умовах",
    "parent_id": "1458",
    "is_final": "1"
  },
  {
    "id": "29546",
    "name": "Т8 Методика очистки і знезараження води в польових умовах",
    "parent_id": "1458",
    "is_final": "1"
  },
  {
    "id": "29547",
    "name": "Т9 Методика оцінки адекватності харчування військовослужбовців за розкладкою продуктів у польових умовах при надзвичайних ситуаціях",
    "parent_id": "1458",
    "is_final": "1"
  }
]