[
  {
    "id": "14710",
    "name": "Т 2 Особливості законодавства у сфері ціноутворення та позначення  роздрібних цін на лікарські засоби та інші товари аптечного асортименту",
    "parent_id": "14726",
    "is_final": "1"
  },
  {
    "id": "14711",
    "name": "Т 3 Загальні положення про працю. Трудовий договір та особливості його укладання на підприємствах фармацевтичної галузі",
    "parent_id": "14726",
    "is_final": "1"
  },
  {
    "id": "14709",
    "name": "Т1 Торгівельна діяльність і захист прав споживачів фармацевтичної продукції. Державний нагляд (контроль) у сфері обігу ЛЗ і ВМП",
    "parent_id": "14726",
    "is_final": "1"
  }
]