[
  {
    "id": "3582",
    "name": "Т1 Спортивна травма плечового поясута ліктя, їх наслідки",
    "parent_id": "21912",
    "is_final": "1"
  },
  {
    "id": "21913",
    "name": "Т10 Модульний контроль 1 Спортивна медицина",
    "parent_id": "21912",
    "is_final": "1"
  },
  {
    "id": "7956",
    "name": "Т10 Спортивна травма ПМК",
    "parent_id": "21912",
    "is_final": "1"
  },
  {
    "id": "3583",
    "name": "Т2. Звичні вивихи та нестабільність плеча, наколінка у спортсменів. С-м відстроченого м’язового болю",
    "parent_id": "21912",
    "is_final": "1"
  },
  {
    "id": "3584",
    "name": "Т3. Типові ушкодження і захворювання кисті та зап'ястка у спортсменів",
    "parent_id": "21912",
    "is_final": "1"
  },
  {
    "id": "7466",
    "name": "Т4 Типові ушкодження кульшового та колінного суглобів у спортсменів (коліно стрибуна, розрив та відрив менісків, нестабільність внаслідок пошкодження зв’язок)",
    "parent_id": "21912",
    "is_final": "1"
  },
  {
    "id": "7467",
    "name": "Т5 Типові ушкодження гомілково-ступневого суглоба та ахіллового сухожилка, тендопатія Ахілла, у спортсменів)",
    "parent_id": "21912",
    "is_final": "1"
  },
  {
    "id": "7468",
    "name": "Т6 Захворювання стоп (п’ятковий апіфізит юніора, плантарнийфасціїт). Гострий та хронічний компартмент-синдром",
    "parent_id": "21912",
    "is_final": "1"
  },
  {
    "id": "7954",
    "name": "Т7 Діагностика і лікування ушкоджень суглобового хряща у спортсменів, бурсити, синовіїти",
    "parent_id": "21912",
    "is_final": "1"
  },
  {
    "id": "7469",
    "name": "Т8 Пошкодження мязів (литкових, квадріцепса, довгого привідного м’яза, малого та середнього сідничного, ілеопсоас-синдром, АRS-синдром",
    "parent_id": "21912",
    "is_final": "1"
  },
  {
    "id": "7955",
    "name": "Т9 Остеоартроз у спортсменів",
    "parent_id": "21912",
    "is_final": "1"
  }
]