[
  {
    "id": "29416",
    "name": "T13 Гіпотензивні (антигіпертензивні) засоби. Гіпертензивні засоби.",
    "parent_id": "25613",
    "is_final": "1"
  },
  {
    "id": "24931",
    "name": "ЗФ_5к_5,5_Фармацевтична хімія_Т3",
    "parent_id": "25613",
    "is_final": "1"
  },
  {
    "id": "30683",
    "name": "ЗФ_5К_5,5_Фармацевтична хімія_Т4",
    "parent_id": "25613",
    "is_final": "1"
  },
  {
    "id": "31408",
    "name": "М4 Т1 Антибіотики гетероциклічної структури. Інгібітори β-лактамаз.",
    "parent_id": "25613",
    "is_final": "1"
  },
  {
    "id": "31409",
    "name": "М4 Т2 Сульфаніламіди",
    "parent_id": "25613",
    "is_final": "1"
  },
  {
    "id": "31410",
    "name": "М4 Т3 Противірусні засоби",
    "parent_id": "25613",
    "is_final": "1"
  },
  {
    "id": "29418",
    "name": "ПМК3 Лікарські засоби, що впливають на нервову, серцево-судинну, видільну системи та систему згортання крові",
    "parent_id": "25613",
    "is_final": "1"
  },
  {
    "id": "31411",
    "name": "ПМК4 Антимікробні препарати (хіміотерапевтичні засоби та антисептики і дезінфектанти)",
    "parent_id": "25613",
    "is_final": "1"
  },
  {
    "id": "29417",
    "name": "Т11 Засоби, що впливають на аферентну нервову систему. Засоби, що стимулюють рецептори аферентних нервових волокон.",
    "parent_id": "25613",
    "is_final": "1"
  },
  {
    "id": "29415",
    "name": "Т12 Кардіотонічні засоби",
    "parent_id": "25613",
    "is_final": "1"
  }
]