[
  {
    "id": "23165",
    "name": "ЗМ- 2 Фармацевтичний аналіз",
    "parent_id": "28844",
    "is_final": "1"
  },
  {
    "id": "23164",
    "name": "ЗМ-1 Фармацевтичний аналіз",
    "parent_id": "28844",
    "is_final": "1"
  },
  {
    "id": "23166",
    "name": "ЗМ-3 Фармацевтичний аналіз",
    "parent_id": "28844",
    "is_final": "1"
  },
  {
    "id": "23167",
    "name": "ЗМ-4 Фармацевтичний аналіз",
    "parent_id": "28844",
    "is_final": "1"
  },
  {
    "id": "23350",
    "name": "ПМК-1 Фармацевтичний аналіз лікарських засобів.",
    "parent_id": "28844",
    "is_final": "1"
  },
  {
    "id": "24895",
    "name": "Фармацевтичний аналіз лікарських засобів Т1",
    "parent_id": "28844",
    "is_final": "1"
  }
]