[
  {
    "id": "31023",
    "name": "Т Module",
    "parent_id": "30831",
    "is_final": "1"
  },
  {
    "id": "31032",
    "name": "Т1 Репродуктивне здоров’я. Біологічні основи репродуктивної системи людини. Фізіологія оваріально-менструальної системи.",
    "parent_id": "30831",
    "is_final": "1"
  },
  {
    "id": "31031",
    "name": "Т2 Методи обстеження репродуктивної системи жінки та чоловіка.",
    "parent_id": "30831",
    "is_final": "1"
  },
  {
    "id": "31030",
    "name": "Т3 Форми природного планування сім’ї.",
    "parent_id": "30831",
    "is_final": "1"
  },
  {
    "id": "31029",
    "name": "Т4 Бар’єрні Методи контрацепції та сперміциди.",
    "parent_id": "30831",
    "is_final": "1"
  },
  {
    "id": "31028",
    "name": "Т5 Гормональна та невідкладна контрацепція.",
    "parent_id": "30831",
    "is_final": "1"
  },
  {
    "id": "31027",
    "name": "Т6 Пролонговані і ін’єкційні контрацептиви.",
    "parent_id": "30831",
    "is_final": "1"
  },
  {
    "id": "31026",
    "name": "Т7 Внутрішньоматкова контрацепція.",
    "parent_id": "30831",
    "is_final": "1"
  },
  {
    "id": "31025",
    "name": "Т8 Метод лактаційної аменореї. Післяродова та післяабортна контрацепція.",
    "parent_id": "30831",
    "is_final": "1"
  },
  {
    "id": "31024",
    "name": "Т9-10 Контрацепція в підлітків, жінок, старше 35 років та жінок з медичними проблемами. Добровільна хірургічна стерилізація.",
    "parent_id": "30831",
    "is_final": "1"
  }
]