[
  {
    "id": "31142",
    "name": "Modul",
    "parent_id": "31138",
    "is_final": "1"
  },
  {
    "id": "31407",
    "name": "Спортивна медицина Модуль 1 ПМК",
    "parent_id": "31138",
    "is_final": "1"
  },
  {
    "id": "31403",
    "name": "Спортивна медицина Тема 1-2",
    "parent_id": "31138",
    "is_final": "1"
  },
  {
    "id": "31404",
    "name": "Спортивна медицина Тема 3-4",
    "parent_id": "31138",
    "is_final": "1"
  },
  {
    "id": "31455",
    "name": "Спортивна медицина Тема 5-6",
    "parent_id": "31138",
    "is_final": "1"
  },
  {
    "id": "31406",
    "name": "Спортивна медицина Тема 7-8",
    "parent_id": "31138",
    "is_final": "1"
  },
  {
    "id": "31459",
    "name": "Спортивна медицина Тема 9",
    "parent_id": "31138",
    "is_final": "1"
  }
]