[
  {
    "id": "34240",
    "name": "Взірець",
    "parent_id": "34239",
    "is_final": "1"
  },
  {
    "id": "38650",
    "name": "Інтегрований курс «Біохімія» 2025 (1 частина)",
    "parent_id": "34239",
    "is_final": "1"
  },
  {
    "id": "40744",
    "name": "Інтегрований курс «Біохімія» 2026 (1 частина)",
    "parent_id": "34239",
    "is_final": "1"
  },
  {
    "id": "40759",
    "name": "Інтегрований курс «Біохімія» 2026 (2 частина)",
    "parent_id": "34239",
    "is_final": "1"
  }
]