[
  {
    "id": "34939",
    "name": "ПМКМедичне право",
    "parent_id": "34652",
    "is_final": "1"
  },
  {
    "id": "34956",
    "name": "Т1Медичне право України",
    "parent_id": "34652",
    "is_final": "1"
  },
  {
    "id": "34955",
    "name": "Т2Юридична регламентація системи охорони здоров’я в Україні",
    "parent_id": "34652",
    "is_final": "1"
  },
  {
    "id": "34962",
    "name": "Т3Правовий статус суб'єктів медичних правовідносин",
    "parent_id": "34652",
    "is_final": "1"
  },
  {
    "id": "34985",
    "name": "Т3Правовий статус суб'єктів медичних правовідносин",
    "parent_id": "34652",
    "is_final": "1"
  },
  {
    "id": "34961",
    "name": "Т4Основи господарської діяльності та страхування у сфері охорони здоров’я",
    "parent_id": "34652",
    "is_final": "1"
  },
  {
    "id": "34954",
    "name": "Т5Правове регулювання окремих видів медичної допомоги",
    "parent_id": "34652",
    "is_final": "1"
  },
  {
    "id": "34960",
    "name": "Т6Дефекти надання медичної допомоги",
    "parent_id": "34652",
    "is_final": "1"
  },
  {
    "id": "34959",
    "name": "Т7Юридична відповідальність у сфері охорони здоров’я",
    "parent_id": "34652",
    "is_final": "1"
  },
  {
    "id": "34958",
    "name": "Т8Захист прав суб’єктів медичних правовідносин",
    "parent_id": "34652",
    "is_final": "1"
  },
  {
    "id": "34654",
    "name": "Взірець",
    "parent_id": "34652",
    "is_final": "1"
  }
]