[
  {
    "id": "35927",
    "name": "Підсумковий модульний контроль із дисципліни «Основи дієтології»",
    "parent_id": "35926",
    "is_final": "1"
  },
  {
    "id": "36726",
    "name": "Т1-2",
    "parent_id": "35926",
    "is_final": "1"
  },
  {
    "id": "36727",
    "name": "Т3-4",
    "parent_id": "35926",
    "is_final": "1"
  },
  {
    "id": "37967",
    "name": "Т 10 Поняття про ампутації, види ампутацій, покази до ампутацій.",
    "parent_id": "35926",
    "is_final": "1"
  },
  {
    "id": "38294",
    "name": "Т11 Ортези, їх види, покази до застосування та вимоги до ортезів, ортезування тулуба, сучасні ортезні пристосування.",
    "parent_id": "35926",
    "is_final": "1"
  },
  {
    "id": "38295",
    "name": "Т12 Види протезів, покази до протезування, процес протезування.",
    "parent_id": "35926",
    "is_final": "1"
  },
  {
    "id": "38354",
    "name": "Т13 Ендопротезування, протезування молочних залоз.",
    "parent_id": "35926",
    "is_final": "1"
  },
  {
    "id": "38355",
    "name": "Т14 Методи оцінки навиків ходи та мобільності пацієнтів",
    "parent_id": "35926",
    "is_final": "1"
  },
  {
    "id": "38638",
    "name": "Т15 Функціональні дослідження при патології суглобів, хребта, периферичних парезах",
    "parent_id": "35926",
    "is_final": "1"
  },
  {
    "id": "38639",
    "name": "Т16 Технічнізасоби при травмах опорно-рухового апарату",
    "parent_id": "35926",
    "is_final": "1"
  },
  {
    "id": "37795",
    "name": "Т7 Силові апарати та їх характеристика.",
    "parent_id": "35926",
    "is_final": "1"
  },
  {
    "id": "37796",
    "name": "Т8 Апарати для відновлення рівноваги тіла та їх характеристика.",
    "parent_id": "35926",
    "is_final": "1"
  },
  {
    "id": "37966",
    "name": "Т9 Вимоги до облаштування кабінетів механотерапії, лікувальної терапії.",
    "parent_id": "35926",
    "is_final": "1"
  }
]