[
  {
    "id": "946",
    "name": "«Онкологія ЩЛД»",
    "parent_id": "364",
    "is_final": "1"
  },
  {
    "id": "1491",
    "name": "Загальна онкологія",
    "parent_id": "364",
    "is_final": "1"
  },
  {
    "id": "3618",
    "name": "Загальна онкологія, Тема №1 Рак губи,  язика, щитовидної залози, лімфогранулематоз. Діагностика, клініка, лікування.",
    "parent_id": "364",
    "is_final": "1"
  },
  {
    "id": "3620",
    "name": "Загальна онкологія. № 5. Рак тіла і шийки матки, рак яєчників. Діагностка, клініка, лікування.",
    "parent_id": "364",
    "is_final": "1"
  },
  {
    "id": "3619",
    "name": "Загальна онкологія. Тема №2. Рак стравоходу, шлунка, підшлункової залози, ободової і прямої кишки. Діагностика, клініка, лікування.",
    "parent_id": "364",
    "is_final": "1"
  },
  {
    "id": "3621",
    "name": "Загальна онкологія. Тема №6. Рак нирки, сечоводу, сечового міхура,",
    "parent_id": "364",
    "is_final": "1"
  },
  {
    "id": "9892",
    "name": "Рак легень, середостіння.",
    "parent_id": "364",
    "is_final": "1"
  },
  {
    "id": "9893",
    "name": "Рак молочної залози. Рак шкіри, меланома.",
    "parent_id": "364",
    "is_final": "1"
  },
  {
    "id": "13094",
    "name": "Тема 1. Онкозахворюваність. Діагностика, лікування злоякісних пухлин ЩЛД. Передрак і рак шкіри голови і шиї.",
    "parent_id": "364",
    "is_final": "1"
  },
  {
    "id": "13095",
    "name": "Тема 2. Передракові захворювання нижньої губи. Рак нижньої губи.",
    "parent_id": "364",
    "is_final": "1"
  },
  {
    "id": "13096",
    "name": "Тема 3. Передракові захворювання слизової оболонки порожнини рота.  Рак слизової оболонки порожнини рота та язика.",
    "parent_id": "364",
    "is_final": "1"
  },
  {
    "id": "13097",
    "name": "Тема 4. Злоякісні пухлини слинних залоз: гістологічна будова, клінічні форми, диференційна діагностика, лікування. Диспансеризація.",
    "parent_id": "364",
    "is_final": "1"
  },
  {
    "id": "13098",
    "name": "Тема 5 Рак і саркома щелеп",
    "parent_id": "364",
    "is_final": "1"
  },
  {
    "id": "13099",
    "name": "Тема 6. Злоякісні пухлини шиї. Лімфаденопатії ЩЛД.",
    "parent_id": "364",
    "is_final": "1"
  }
]